mplviz/__init__.py
mplviz/viz.py
mplviz-0.3.dist-info/licenses/LICENSE
mplviz-0.3.dist-info/METADATA
mplviz-0.3.dist-info/WHEEL
mplviz-0.3.dist-info/top_level.txt
mplviz-0.3.dist-info/RECORD
