Metadata-Version: 2.4
Name: mplviz
Version: 0.3
Summary: A fluent wrapper around matplotlib for easy, expressive visualizations
Home-page: https://github.com/BBEK-Anand/mplviz
Author: BBEK-Anand
License: MIT
Project-URL: Homepage, https://github.com/BBEK-Anand/mplviz
Project-URL: Repository, https://github.com/BBEK-Anand/mplviz
Project-URL: Issues, https://github.com/BBEK-Anand/mplviz/issues
Keywords: matplotlib,visualization,wrapper,plotting
Classifier: Development Status :: 3 - Alpha
Classifier: Intended Audience :: Developers
Classifier: Intended Audience :: Science/Research
Classifier: License :: OSI Approved :: MIT License
Classifier: Programming Language :: Python :: 3
Classifier: Programming Language :: Python :: 3.8
Classifier: Programming Language :: Python :: 3.9
Classifier: Topic :: Scientific/Engineering :: Visualization
Classifier: Framework :: Matplotlib
Requires-Python: >=3.7
License-File: LICENSE
Requires-Dist: matplotlib>=3.6.0
Requires-Dist: numpy>=1.18.0
Requires-Dist: ipython>=7.0.0
Provides-Extra: docs
Requires-Dist: sphinx; extra == "docs"
Requires-Dist: sphinx_rtd_theme; extra == "docs"
Requires-Dist: myst-parser; extra == "docs"
Dynamic: home-page
Dynamic: license-file
Dynamic: requires-python
